system_compat_checker/__init__.py
system_compat_checker/__main__.py
system_compat_checker/cli.py
system_compat_checker/groq_analyzer.py
system_compat_checker/install_check.py
system_compat_checker/optimized_system_info.ps1
system_compat_checker/posix_info.py
system_compat_checker/storage.py
system_compat_checker/system_info.py
system_compat_checker/windows_info.py
system_compat_checker-1.0.2.dist-info/licenses/LICENSE
system_compat_checker-1.0.2.dist-info/METADATA
system_compat_checker-1.0.2.dist-info/WHEEL
system_compat_checker-1.0.2.dist-info/entry_points.txt
system_compat_checker-1.0.2.dist-info/top_level.txt
system_compat_checker-1.0.2.dist-info/RECORD
