Metadata-Version: 2.4
Name: system-compat-checker
Version: 1.0.2
Summary: A cross-platform CLI tool for checking system compatibility with AI-powered analysis
Home-page: https://github.com/yourusername/system-compat-checker
Author: System Compatibility Checker Team
Author-email: System Compatibility Checker Team <contact@system-compat-checker.dev>
Maintainer-email: System Compatibility Checker Team <contact@system-compat-checker.dev>
License-Expression: MIT
Project-URL: Homepage, https://github.com/yourusername/system-compat-checker
Project-URL: Repository, https://github.com/yourusername/system-compat-checker
Project-URL: Documentation, https://github.com/yourusername/system-compat-checker/tree/main/docs
Project-URL: Bug Reports, https://github.com/yourusername/system-compat-checker/issues
Keywords: system,compatibility,checker,hardware,requirements,analysis,CLI
Classifier: Development Status :: 5 - Production/Stable
Classifier: Intended Audience :: Developers
Classifier: Intended Audience :: System Administrators
Classifier: Topic :: System :: Systems Administration
Classifier: Topic :: Software Development :: Testing
Classifier: Topic :: Utilities
Classifier: Programming Language :: Python :: 3
Classifier: Programming Language :: Python :: 3.8
Classifier: Programming Language :: Python :: 3.9
Classifier: Programming Language :: Python :: 3.10
Classifier: Programming Language :: Python :: 3.11
Classifier: Programming Language :: Python :: 3.12
Classifier: Operating System :: OS Independent
Classifier: Operating System :: Microsoft :: Windows
Classifier: Operating System :: POSIX :: Linux
Classifier: Operating System :: MacOS
Classifier: Environment :: Console
Requires-Python: >=3.8
License-File: LICENSE
Requires-Dist: click>=8.0.0
Requires-Dist: requests>=2.28.0
Requires-Dist: keyring>=24.0.0
Requires-Dist: rich>=13.0.0
Requires-Dist: psutil>=5.9.0
Requires-Dist: platformdirs>=3.0.0
Provides-Extra: dev
Requires-Dist: pytest>=7.0.0; extra == "dev"
Requires-Dist: pytest-cov>=4.0.0; extra == "dev"
Requires-Dist: flake8>=5.0.0; extra == "dev"
Requires-Dist: mypy>=1.0.0; extra == "dev"
Requires-Dist: black>=22.0.0; extra == "dev"
Dynamic: author
Dynamic: home-page
Dynamic: license-file
Dynamic: requires-python
